lektor_textile.py
lektor_textile-0.2.dist-info/DESCRIPTION.rst
lektor_textile-0.2.dist-info/METADATA
lektor_textile-0.2.dist-info/RECORD
lektor_textile-0.2.dist-info/WHEEL
lektor_textile-0.2.dist-info/entry_points.txt
lektor_textile-0.2.dist-info/metadata.json
lektor_textile-0.2.dist-info/top_level.txt
