Metadata-Version: 2.0
Name: lektor-textile
Version: 0.2
Summary: Adds Textile markup support to Lektor (as standalone files).
Home-page: http://github.com/svafn/lektor-textile
Author: Viktor Semenyuk
Author-email: svafn1@gmail.com
License: MIT
Platform: UNKNOWN
Requires-Dist: textile
